setup.py
Lib0201/__init__.py
Lib0201.egg-info/PKG-INFO
Lib0201.egg-info/SOURCES.txt
Lib0201.egg-info/dependency_links.txt
Lib0201.egg-info/top_level.txt