Metadata-Version: 1.1
Name: Lib0201
Version: 0.0.1
Summary: Tes
Home-page: UNKNOWN
Author: Vijayakumar Kanniah
Author-email: x21188955@student.ncirl.ie
License: UNKNOWN
Keywords: logging
Platform: UNKNOWN
Classifier: Development Status :: 5 - Production/Stable
Classifier: Intended Audience :: Education
Classifier: Operating System :: Microsoft :: Windows :: Windows 10
Classifier: License :: OSI Approved :: MIT License
Classifier: Programming Language :: Python :: 3
